armorapi/__init__.py
armorapi-0.0.3.dist-info/LICENSE
armorapi-0.0.3.dist-info/METADATA
armorapi-0.0.3.dist-info/WHEEL
armorapi-0.0.3.dist-info/top_level.txt
armorapi-0.0.3.dist-info/RECORD
