Metadata-Version: 2.1
Name: armorapi
Version: 0.0.3
Summary: module for working with the armorapi
Home-page: https://github.com/gingebot/armorapi
Author: gingebot
Author-email: gingebot@gmail.com
License: UNKNOWN
Project-URL: Bug Tracker, https://github.com/gingebot/armorapi/issues
Platform: UNKNOWN
Classifier: Programming Language :: Python :: 3
Classifier: License :: OSI Approved :: Apache Software License
Classifier: Operating System :: OS Independent
Requires-Python: >=3.6
License-File: LICENSE
Requires-Dist: requests
Requires-Dist: bs4
